red.py
white.py
white-0.1.2.dist-info/DESCRIPTION.rst
white-0.1.2.dist-info/METADATA
white-0.1.2.dist-info/RECORD
white-0.1.2.dist-info/WHEEL
white-0.1.2.dist-info/entry_points.txt
white-0.1.2.dist-info/metadata.json
white-0.1.2.dist-info/top_level.txt
